stats.py
Statistics_pyt-1.1.dist-info/METADATA
Statistics_pyt-1.1.dist-info/WHEEL
Statistics_pyt-1.1.dist-info/top_level.txt
Statistics_pyt-1.1.dist-info/RECORD
