Metadata-Version: 2.1
Name: Statistics-pyt
Version: 1.1
Summary: To find Mean,Median,Mode of the given numbers
Home-page: https://github.com/Vishalkanna2001/statistics-pyt
Author: Vishal Kanna AJK
Author-email: vishalkanna.k@outlook.com
License: UNKNOWN
Platform: UNKNOWN
Classifier: Programming Language :: Python :: 3.5
Classifier: Programming Language :: Python :: 3.6
Classifier: Programming Language :: Python :: 3.7
Classifier: Programming Language :: Python :: 3.8
Classifier: Operating System :: OS Independent
